ffhelper/__init__.py
ffhelper/__main__.py
ffhelper/add_text.py
ffhelper/cli.py
ffhelper/combine.py
ffhelper/dump.py
ffhelper/im2vid.py
ffhelper/join.py
ffhelper-0.1.5.dist-info/LICENSE
ffhelper-0.1.5.dist-info/METADATA
ffhelper-0.1.5.dist-info/WHEEL
ffhelper-0.1.5.dist-info/entry_points.txt
ffhelper-0.1.5.dist-info/top_level.txt
ffhelper-0.1.5.dist-info/RECORD
