Metadata-Version: 2.1
Name: ffhelper
Version: 0.1.5
Summary: ffhelper is a ffmpeg helper
Home-page: https://github.com/jayshihchou/ffmpeg_helper
Author: Chou, Shih-Chieh
Author-email: jayshihchou@gmail.com
License: MIT
Keywords: ffmpeg,ffmpeg_helper,ffhelper
Platform: UNKNOWN
Classifier: License :: OSI Approved :: MIT License
Classifier: Programming Language :: Python
Classifier: Programming Language :: Python :: 3
Classifier: Programming Language :: Python :: 3.7
Classifier: Programming Language :: Python :: 3.8
Classifier: Programming Language :: Python :: 3.9
Classifier: Operating System :: Microsoft :: Windows
Classifier: Operating System :: POSIX :: Linux
Classifier: Operating System :: MacOS
Requires-Python: >=3.6
License-File: LICENSE
